analogvnn/__init__.py
analogvnn/py.typed
analogvnn/backward/BackwardFunction.py
analogvnn/backward/BackwardIdentity.py
analogvnn/backward/BackwardModule.py
analogvnn/backward/BackwardUsingForward.py
analogvnn/backward/__init__.py
analogvnn/fn/__init__.py
analogvnn/fn/dirac_delta.py
analogvnn/fn/reduce_precision.py
analogvnn/fn/test.py
analogvnn/fn/to_matrix.py
analogvnn/fn/train.py
analogvnn/graph/AccumulateGrad.py
analogvnn/graph/AcyclicDirectedGraph.py
analogvnn/graph/ArgsKwargs.py
analogvnn/graph/BackwardGraph.py
analogvnn/graph/ForwardGraph.py
analogvnn/graph/GraphEnum.py
analogvnn/graph/ModelGraph.py
analogvnn/graph/ModelGraphState.py
analogvnn/graph/__init__.py
analogvnn/graph/to_graph_viz_digraph.py
analogvnn/nn/Linear.py
analogvnn/nn/__init__.py
analogvnn/nn/activation/Activation.py
analogvnn/nn/activation/BinaryStep.py
analogvnn/nn/activation/ELU.py
analogvnn/nn/activation/Gaussian.py
analogvnn/nn/activation/Identity.py
analogvnn/nn/activation/ReLU.py
analogvnn/nn/activation/SiLU.py
analogvnn/nn/activation/Sigmoid.py
analogvnn/nn/activation/Tanh.py
analogvnn/nn/activation/__init__.py
analogvnn/nn/module/FullSequential.py
analogvnn/nn/module/Layer.py
analogvnn/nn/module/Model.py
analogvnn/nn/module/Sequential.py
analogvnn/nn/module/__init__.py
analogvnn/nn/noise/GaussianNoise.py
analogvnn/nn/noise/LaplacianNoise.py
analogvnn/nn/noise/Noise.py
analogvnn/nn/noise/PoissonNoise.py
analogvnn/nn/noise/UniformNoise.py
analogvnn/nn/noise/__init__.py
analogvnn/nn/normalize/Clamp.py
analogvnn/nn/normalize/LPNorm.py
analogvnn/nn/normalize/Normalize.py
analogvnn/nn/normalize/__init__.py
analogvnn/nn/precision/Precision.py
analogvnn/nn/precision/ReducePrecision.py
analogvnn/nn/precision/StochasticReducePrecision.py
analogvnn/nn/precision/__init__.py
analogvnn/parameter/PseudoParameter.py
analogvnn/parameter/__init__.py
analogvnn/utils/TensorboardModelLog.py
analogvnn/utils/__init__.py
analogvnn/utils/common_types.py
analogvnn/utils/get_model_summaries.py
analogvnn-1.0.8.dist-info/LICENSE
analogvnn-1.0.8.dist-info/WHEEL
analogvnn-1.0.8.dist-info/METADATA
analogvnn-1.0.8.dist-info/RECORD
