Metadata-Version: 2.1
Name: analogvnn
Version: 1.0.8
Summary: A fully modular framework for modeling and optimizing analog/photonic neural networks
Keywords: deep-learning,analog,photonics,neural-network,framework,pytorch
Author-email: Vivswan Shah <vivswanshah@pitt.edu>
Maintainer-email: Vivswan Shah <vivswanshah@pitt.edu>
Requires-Python: >=3.7
Classifier: Development Status :: 5 - Production/Stable
Classifier: Intended Audience :: Developers
Classifier: Intended Audience :: Science/Research
Classifier: Topic :: Software Development :: Build Tools
Classifier: Topic :: Scientific/Engineering :: Artificial Intelligence
Classifier: Topic :: Software Development :: Libraries :: Python Modules
Classifier: License :: OSI Approved :: Mozilla Public License 2.0 (MPL 2.0)
Classifier: Programming Language :: Python :: 3
Classifier: Programming Language :: Python :: 3.7
Classifier: Programming Language :: Python :: 3.8
Classifier: Programming Language :: Python :: 3.9
Classifier: Programming Language :: Python :: 3.10
Classifier: Programming Language :: Python :: 3 :: Only
Requires-Dist: dataclasses
Requires-Dist: scipy
Requires-Dist: numpy>=1.16.5
Requires-Dist: networkx
Requires-Dist: importlib-metadata<5.0.0,>=2.0.0; python_version < '3.8'
Requires-Dist: analogvnn[full,dev,doc,test] ; extra == "all"
Requires-Dist: setuptools>=61.0.0 ; extra == "dev"
Requires-Dist: flit ; extra == "dev"
Requires-Dist: build ; extra == "dev"
Requires-Dist: twine ; extra == "dev"
Requires-Dist: johnnydep ; extra == "dev"
Requires-Dist: sphinx>=4.2.0 ; extra == "doc"
Requires-Dist: sphinx-autobuild ; extra == "doc"
Requires-Dist: rst-to-myst[sphinx] ; extra == "doc"
Requires-Dist: furo ; extra == "doc"
Requires-Dist: myst_parser ; extra == "doc"
Requires-Dist: sphinx-rtd-theme ; extra == "doc"
Requires-Dist: sphinx-autoapi ; extra == "doc"
Requires-Dist: sphinx-copybutton ; extra == "doc"
Requires-Dist: sphinx-notfound-page ; extra == "doc"
Requires-Dist: sphinx-inline-tabs ; extra == "doc"
Requires-Dist: sphinxext-opengraph ; extra == "doc"
Requires-Dist: sphinxcontrib-katex ; extra == "doc"
Requires-Dist: flake8 ; extra == "flake8"
Requires-Dist: flake8-docstrings ; extra == "flake8"
Requires-Dist: flake8-quotes ; extra == "flake8"
Requires-Dist: flake8-bugbear ; extra == "flake8"
Requires-Dist: flake8-comprehensions ; extra == "flake8"
Requires-Dist: flake8-executable ; extra == "flake8"
Requires-Dist: flake8-coding ; extra == "flake8"
Requires-Dist: flake8-return ; extra == "flake8"
Requires-Dist: flake8-deprecated ; extra == "flake8"
Requires-Dist: tensorflow ; extra == "full"
Requires-Dist: tensorboard ; extra == "full"
Requires-Dist: torchinfo ; extra == "full"
Requires-Dist: graphviz ; extra == "full"
Requires-Dist: analogvnn[flake8] ; extra == "test"
Project-URL: Author, https://vivswan.github.io/
Project-URL: Bug Reports, https://github.com/Vivswan/AnalogVNN/issues
Project-URL: Documentation, https://analogvnn.readthedocs.io/en/latest/
Project-URL: Homepage, https://github.com/Vivswan/AnalogVNN
Project-URL: Say Thanks!, https://vivswan.github.io/
Project-URL: Source, https://github.com/Vivswan/AnalogVNN
Provides-Extra: all
Provides-Extra: dev
Provides-Extra: doc
Provides-Extra: flake8
Provides-Extra: full
Provides-Extra: test
